__init__.py
pilflow/__init__.py
pilflow/contexts/__init__.py
pilflow/contexts/blur.py
pilflow/contexts/resize.py
pilflow/contexts/resolution_decision.py
pilflow/contexts/sharpen.py
pilflow/core/__init__.py
pilflow/core/context.py
pilflow/core/image_pack.py
pilflow/core/operation.py
pilflow/operations/__init__.py
pilflow/operations/blur.py
pilflow/operations/decide_resolution.py
pilflow/operations/resize.py
pilflow/operations/sharpen.py
pilflow-0.1.0.dist-info/LICENSE
pilflow-0.1.0.dist-info/METADATA
pilflow-0.1.0.dist-info/WHEEL
pilflow-0.1.0.dist-info/top_level.txt
pilflow-0.1.0.dist-info/RECORD
