Metadata-Version: 2.1
Name: pilflow
Version: 0.1.0
Summary: A Pillow-based image processing pipeline project.
Author-email: Cheng Yanru <yanru@cyanru.com>
License: MIT
Classifier: Development Status :: 4 - Beta
Classifier: Intended Audience :: Developers
Classifier: License :: OSI Approved :: MIT License
Classifier: Operating System :: OS Independent
Classifier: Programming Language :: Python
Classifier: Programming Language :: Python :: 3
Classifier: Programming Language :: Python :: 3.8
Classifier: Programming Language :: Python :: 3.9
Classifier: Programming Language :: Python :: 3.10
Classifier: Programming Language :: Python :: 3.11
Classifier: Topic :: Software Development :: Libraries :: Python Modules
Classifier: Topic :: Multimedia :: Graphics
Requires-Python: >=3.8
License-File: LICENSE
Requires-Dist: Pillow >=6.2.1
Requires-Dist: jinnang >=0.2.0
Provides-Extra: dev
Requires-Dist: pytest >=7.0.0 ; extra == 'dev'
Requires-Dist: pytest-cov >=4.0.0 ; extra == 'dev'
Requires-Dist: requests >=2.28.0 ; extra == 'dev'
Requires-Dist: build >=1.0.0 ; extra == 'dev'
Requires-Dist: twine >=5.0.0 ; extra == 'dev'
